{"name":"Logout scenario","id":"logout;logout-scenario","testSteps":[{"number":1,"description":"Example: {email\u003dtest, password\u003dtest}","duration":19921,"startTime":"2022-05-20T13:32:56.721771100+07:00[Asia/Bangkok]","result":"SUCCESS","precondition":false,"level":0,"lineNumber":15,"children":[{"number":2,"description":"Given I click the login button","duration":679,"startTime":"2022-05-20T13:33:04.790484600+07:00[Asia/Bangkok]","result":"SUCCESS","precondition":false,"level":1},{"number":3,"description":"When I input the \"test\" email","duration":4848,"startTime":"2022-05-20T13:33:05.472940600+07:00[Asia/Bangkok]","result":"SUCCESS","precondition":false,"level":1},{"number":4,"description":"And I input the \"test\" password","duration":3858,"startTime":"2022-05-20T13:33:10.323290500+07:00[Asia/Bangkok]","result":"SUCCESS","precondition":false,"level":1},{"number":5,"description":"And I click again the login button","duration":659,"startTime":"2022-05-20T13:33:14.185254800+07:00[Asia/Bangkok]","result":"SUCCESS","precondition":false,"level":1},{"number":6,"description":"Then I get a result","duration":1163,"startTime":"2022-05-20T13:33:14.847696500+07:00[Asia/Bangkok]","result":"SUCCESS","precondition":false,"level":1},{"number":7,"description":"And I click logout button","duration":274,"startTime":"2022-05-20T13:33:16.014477+07:00[Asia/Bangkok]","result":"SUCCESS","precondition":false,"level":1}]}],"userStory":{"id":"logout","storyName":"Logout","path":"file:///D:/My%20Documents/File%20Difa/TI%20Semester%206%20Kampus%20Merdeka%20Alterra/Tugas/Mini_Project/Praktikum/Mini-Project-Mobile/src/test/resources/features/Logout.feature","narrative":"  As an User\n  I want to success login\n  So that I can logut","type":"feature"},"featureTag":{"name":"Features/Logout","type":"feature","displayName":"Features/Logout"},"title":"Logout scenario","description":"","tags":[{"name":"Logout","type":"feature","displayName":"Logout"}],"startTime":"2022-05-20T13:32:56.709764400+07:00[Asia/Bangkok]","duration":19935,"projectKey":"","isManualTestingUpToDate":false,"dataTable":{"headers":["email","password"],"rows":[{"values":["test","test"],"lineNumber":15,"result":"SUCCESS"}],"predefinedRows":true,"scenarioOutline":"Given I click the login button\n\rWhen I input the \"\u003cemail\u003e\" email\n\rAnd I input the \"\u003cpassword\u003e\" password\n\rAnd I click again the login button\n\rThen I get a result\n\rAnd I click logout button\n\r","dataSetDescriptors":[{"startRow":0,"rowCount":0,"name":"","description":""}]},"manual":false,"testSource":"Cucumber","result":"SUCCESS","scenarioOutline":"Given I click the login button\r\nWhen I input the \"\u003cemail\u003e\" email\r\nAnd I input the \"\u003cpassword\u003e\" password\r\nAnd I click again the login button\r\nThen I get a result\r\nAnd I click logout button"}